{"type":"View","props":{"y":0,"x":0,"width":600,"top":50,"right":0,"isPopupCenter":false,"isModal":true,"height":1000},"compId":2,"child":[{"type":"Sprite","props":{"y":2,"x":0,"texture":"view1.0/view (8).png"},"compId":86},{"type":"Animation","props":{"y":76,"x":125,"width":404,"var":"ani_car","scaleY":0.9,"scaleX":0.9,"height":404,"autoPlay":true},"compId":83},{"type":"Label","props":{"y":87,"x":136,"width":291,"var":"la_name","valign":"middle","text":"搅拌车","height":30,"fontSize":30,"font":"Microsoft YaHei","color":"#00ffff","bold":false,"align":"center"},"compId":87},{"type":"Button","props":{"y":614,"x":75,"var":"bu0_0","stateNum":2,"skin":"view1.0/bu_1.png","labelSize":24,"labelColors":"#00ffff,#00ffff,#00ffff,#00ffff,#00ffff"},"compId":92,"child":[{"type":"Label","props":{"y":12,"x":86,"text":"进站","fontSize":20,"color":"#ffffff"},"compId":106}]},{"type":"Button","props":{"y":614,"x":498,"var":"bu0_1","stateNum":2,"skin":"view1.0/bu_1.png","skewY":180,"labelSize":24,"labelColors":"#00ffff,#00ffff,#00ffff,#00ffff,#00ffff"},"compId":93,"child":[{"type":"Label","props":{"y":22,"x":106,"text":"出站","skewY":180,"fontSize":20,"color":"#ffffff","anchorY":0.5,"anchorX":0.5},"compId":109}]},{"type":"Button","props":{"y":708.5,"x":76,"var":"bu_1_0","stateNum":2,"skin":"view1.0/bu_1.png","labelSize":24,"labelColors":"#00ffff,#00ffff,#00ffff,#00ffff,#00ffff"},"compId":94,"child":[{"type":"Label","props":{"y":22,"x":106,"text":"装料","fontSize":20,"color":"#ffffff","anchorY":0.5,"anchorX":0.5},"compId":108}]},{"type":"Button","props":{"y":708,"x":499,"var":"bu_1_1","stateNum":2,"skin":"view1.0/bu_1.png","skewY":180,"labelSize":24,"labelColors":"#00ffff,#00ffff,#00ffff,#00ffff,#00ffff"},"compId":95,"child":[{"type":"Label","props":{"y":22,"x":106,"text":"卸料","skewY":180,"fontSize":20,"color":"#ffffff","anchorY":0.5,"anchorX":0.5},"compId":110}]},{"type":"Button","props":{"y":802,"x":75,"var":"bu_2_0","stateNum":2,"skin":"view1.0/bu_1.png","labelSize":24,"labelColors":"#00ffff,#00ffff,#00ffff,#00ffff,#00ffff"},"compId":96,"child":[{"type":"Label","props":{"y":22,"x":106,"text":"过磅","fontSize":20,"color":"#ffffff","anchorY":0.5,"anchorX":0.5},"compId":111}]},{"type":"Button","props":{"y":802,"x":498,"var":"bu_2_1","stateNum":2,"skin":"view1.0/bu_1.png","skewY":180,"labelSize":24,"labelColors":"#00ffff,#00ffff,#00ffff,#00ffff,#00ffff"},"compId":97,"child":[{"type":"Label","props":{"y":22,"x":106,"text":"回皮","skewY":180,"fontSize":20,"color":"#ffffff","anchorY":0.5,"anchorX":0.5},"compId":112}]},{"type":"Label","props":{"y":431,"x":183,"width":94,"text":"车牌号码：","height":24,"fontSize":20,"color":"#00ffff","align":"right"},"compId":98},{"type":"Label","props":{"y":473,"x":191,"width":94,"text":"驾驶员：","height":24,"fontSize":20,"color":"#00ffff","align":"right"},"compId":99},{"type":"Label","props":{"y":514,"x":183,"width":92,"text":"运输货物：","height":24,"fontSize":20,"color":"#00ffff","align":"right"},"compId":100},{"type":"Label","props":{"y":431,"x":302,"width":215,"var":"la_desc0","text":"京BKF393（满载）","height":24,"fontSize":20,"color":"#00ffff","align":"left"},"compId":101},{"type":"Label","props":{"y":473,"x":302,"width":215,"var":"la_desc1","text":"魏大宝","height":24,"fontSize":20,"color":"#00ffff","align":"left"},"compId":102},{"type":"Label","props":{"y":514,"x":302,"width":215,"var":"la_desc2","text":"水泥","height":24,"fontSize":20,"color":"#00ffff","align":"left"},"compId":103},{"type":"Sprite","props":{"y":75,"x":489,"texture":"view1.0/bu_close1.png","scaleY":1,"scaleX":1},"compId":113},{"type":"Sprite","props":{"y":42,"x":432,"width":100,"var":"bu_close","height":100},"compId":114}],"loadList":["view1.0/view (8).png","view1.0/bu_1.png","view1.0/bu_close1.png"],"loadList3D":[]}